eternal_radio_player/__init__.py
eternal_radio_player/__main__.py
eternal_radio_player/_version.py
eternal_radio_player/cli.py
eternal_radio_player/config.py
eternal_radio_player/constants.py
eternal_radio_player/exceptions.py
eternal_radio_player/i18n.py
eternal_radio_player/player.py
eternal_radio_player/stream.py
eternal_radio_player/utils.py
eternal_radio_player/gui/__init__.py
eternal_radio_player/gui/gui.py
eternal_radio_player/gui/logging_.py
eternal_radio_player/gui/widgets.py
eternal_radio_player/gui/generated/__init__.py
eternal_radio_player/gui/generated/main_window.py
eternal_radio_player/gui/generated/resources_rc.py
eternal_radio_player-0.1.3.dist-info/LICENSE
eternal_radio_player-0.1.3.dist-info/METADATA
eternal_radio_player-0.1.3.dist-info/WHEEL
eternal_radio_player-0.1.3.dist-info/entry_points.txt
eternal_radio_player-0.1.3.dist-info/top_level.txt
eternal_radio_player-0.1.3.dist-info/RECORD
