Metadata-Version: 2.1
Name: eternal-radio-player
Version: 0.1.3
Summary: A desktop app for the online radio station Eternal Radio
Home-page: https://github.com/alexitx/eternal-radio-player
Author: alexitx
Author-email: alexander@alexitx.com
License: GPLv3+
Project-URL: Bug Tracker, https://github.com/alexitx/eternal-radio-player/issues
Project-URL: Source, https://github.com/alexitx/eternal-radio-player
Keywords: audio,eternal radio,http,music,online radio,player,radio,stream
Platform: UNKNOWN
Classifier: Development Status :: 4 - Beta
Classifier: Environment :: Console
Classifier: Environment :: Win32 (MS Windows)
Classifier: Environment :: X11 Applications :: Qt
Classifier: Intended Audience :: End Users/Desktop
Classifier: License :: OSI Approved :: GNU General Public License v3 or later (GPLv3+)
Classifier: Natural Language :: English
Classifier: Operating System :: OS Independent
Classifier: Programming Language :: Python :: 3
Classifier: Programming Language :: Python :: 3 :: Only
Classifier: Programming Language :: Python :: 3.7
Classifier: Programming Language :: Python :: 3.8
Classifier: Programming Language :: Python :: 3.9
Classifier: Programming Language :: Python :: 3.10
Classifier: Programming Language :: Python :: Implementation :: CPython
Classifier: Topic :: Multimedia :: Sound/Audio :: Players
Requires-Python: >=3.7
License-File: LICENSE
Requires-Dist: miniaudio (>=1.46)
Requires-Dist: numpy (>=1.21.5)
Requires-Dist: platformdirs (>=2.5.1)
Requires-Dist: requests (>=2.27.1)
Requires-Dist: schema (>=0.7.5)
Requires-Dist: sounddevice (>=0.4.4)
Requires-Dist: timeago (>=1.0.15)
Provides-Extra: gui
Requires-Dist: pyqtdarktheme (>=1.1.0) ; extra == 'gui'
Requires-Dist: PySide6 (>=6.2.3) ; extra == 'gui'
